PythonZhengzebiaodashiCaozuoZhinan/README.md
PythonZhengzebiaodashiCaozuoZhinan/__init__.py
PythonZhengzebiaodashiCaozuoZhinan/__main__.py
PythonZhengzebiaodashiCaozuoZhinan/file.epub
PythonZhengzebiaodashiCaozuoZhinan/index.html
PythonZhengzebiaodashiCaozuoZhinan/css/__init__.py
PythonZhengzebiaodashiCaozuoZhinan/css/annotations.css
PythonZhengzebiaodashiCaozuoZhinan/css/main.css
PythonZhengzebiaodashiCaozuoZhinan/css/normalize.css
PythonZhengzebiaodashiCaozuoZhinan/css/popup.css
PythonZhengzebiaodashiCaozuoZhinan/font/__init__.py
PythonZhengzebiaodashiCaozuoZhinan/font/fontello.eot
PythonZhengzebiaodashiCaozuoZhinan/font/fontello.svg
PythonZhengzebiaodashiCaozuoZhinan/font/fontello.ttf
PythonZhengzebiaodashiCaozuoZhinan/font/fontello.woff
PythonZhengzebiaodashiCaozuoZhinan/img/__init__.py
PythonZhengzebiaodashiCaozuoZhinan/img/annotator-glyph-sprite.png
PythonZhengzebiaodashiCaozuoZhinan/img/annotator-icon-sprite.png
PythonZhengzebiaodashiCaozuoZhinan/img/apple-touch-icon.png
PythonZhengzebiaodashiCaozuoZhinan/img/cancelfullscreen.png
PythonZhengzebiaodashiCaozuoZhinan/img/close.png
PythonZhengzebiaodashiCaozuoZhinan/img/fullscreen.png
PythonZhengzebiaodashiCaozuoZhinan/img/loader.gif
PythonZhengzebiaodashiCaozuoZhinan/img/menu-icon.png
PythonZhengzebiaodashiCaozuoZhinan/img/save.png
PythonZhengzebiaodashiCaozuoZhinan/img/saved.png
PythonZhengzebiaodashiCaozuoZhinan/img/settings-s.png
PythonZhengzebiaodashiCaozuoZhinan/img/settings.png
PythonZhengzebiaodashiCaozuoZhinan/img/star.png
PythonZhengzebiaodashiCaozuoZhinan/js/__init__.py
PythonZhengzebiaodashiCaozuoZhinan/js/epub.js
PythonZhengzebiaodashiCaozuoZhinan/js/epub.min.js
PythonZhengzebiaodashiCaozuoZhinan/js/epub.min.map
PythonZhengzebiaodashiCaozuoZhinan/js/hooks.min.js
PythonZhengzebiaodashiCaozuoZhinan/js/hooks.min.map
PythonZhengzebiaodashiCaozuoZhinan/js/reader.js
PythonZhengzebiaodashiCaozuoZhinan/js/reader.js.map
PythonZhengzebiaodashiCaozuoZhinan/js/reader.min.js
python_zhengzebiaodashi_caozuo_zhinan-2024.3.1.0.dist-info/METADATA
python_zhengzebiaodashi_caozuo_zhinan-2024.3.1.0.dist-info/WHEEL
python_zhengzebiaodashi_caozuo_zhinan-2024.3.1.0.dist-info/entry_points.txt
python_zhengzebiaodashi_caozuo_zhinan-2024.3.1.0.dist-info/top_level.txt
python_zhengzebiaodashi_caozuo_zhinan-2024.3.1.0.dist-info/RECORD
